odoo/addons/login_all_company/README.rst
odoo/addons/login_all_company/__init__.py
odoo/addons/login_all_company/__manifest__.py
odoo/addons/login_all_company/i18n/login_all_company.pot
odoo/addons/login_all_company/readme/CONTRIBUTORS.rst
odoo/addons/login_all_company/readme/DESCRIPTION.rst
odoo/addons/login_all_company/static/description/icon.png
odoo/addons/login_all_company/static/description/index.html
odoo/addons/login_all_company/static/src/js/client.js
odoo/addons/login_all_company/templates/assets.xml
odoo14_addon_login_all_company-14.0.1.0.1.dist-info/METADATA
odoo14_addon_login_all_company-14.0.1.0.1.dist-info/WHEEL
odoo14_addon_login_all_company-14.0.1.0.1.dist-info/top_level.txt
odoo14_addon_login_all_company-14.0.1.0.1.dist-info/RECORD
